MANIFEST.in
README.md
UNLICENSE
clear_cache.jpg
manage.py
setup.py
clear_cache/__init__.py
clear_cache/models.py
clear_cache/tests.py
clear_cache/views.py
django_clear_cache.egg-info/PKG-INFO
django_clear_cache.egg-info/SOURCES.txt
django_clear_cache.egg-info/dependency_links.txt
django_clear_cache.egg-info/not-zip-safe
django_clear_cache.egg-info/requires.txt
django_clear_cache.egg-info/top_level.txt