Metadata-Version: 1.0
Name: django-clear-cache
Version: 0.2
Summary: A simple Django management command which clears your cache.
Home-page: https://github.com/rdegges/django-clear-cache
Author: Randall Degges
Author-email: rdegges@gmail.com
License: UNLICENSE
Keywords: django cache management memcached clear
Platform: UNKNOWN
